imageai/__init__.py
imageai/Classification/__init__.py
imageai/Classification/imagenet_classes.txt
imageai/Classification/Custom/__init__.py
imageai/Classification/Custom/data_transformation.py
imageai/Classification/Custom/training_params.py
imageai/Detection/__init__.py
imageai/Detection/coco91_classes.txt
imageai/Detection/coco_classes.txt
imageai/Detection/Custom/__init__.py
imageai/Detection/Custom/yolo/__init__.py
imageai/Detection/Custom/yolo/compute_loss.py
imageai/Detection/Custom/yolo/custom_anchors.py
imageai/Detection/Custom/yolo/dataset.py
imageai/Detection/Custom/yolo/metric.py
imageai/Detection/Custom/yolo/validate.py
imageai/backend_check/__init__.py
imageai/backend_check/backend_check.py
imageai/backend_check/model_extension.py
imageai/densenet121/__init__.py
imageai/inceptionv3/__init__.py
imageai/mobilenetv2/__init__.py
imageai/resnet50/__init__.py
imageai/retinanet/__init__.py
imageai/retinanet/utils.py
imageai/yolov3/__init__.py
imageai/yolov3/tiny_yolov3.py
imageai/yolov3/utils.py
imageai/yolov3/yolov3.py
imageai-3.0.3.dist-info/LICENSE
imageai-3.0.3.dist-info/METADATA
imageai-3.0.3.dist-info/WHEEL
imageai-3.0.3.dist-info/top_level.txt
imageai-3.0.3.dist-info/RECORD
