Metadata-Version: 2.1
Name: imageai
Version: 3.0.3
Summary: A python library built to empower developers to build applications and systems  with self-contained Computer Vision capabilities
Home-page: https://github.com/OlafenwaMoses/ImageAI
Author: Moses Olafenwa
Author-email: guymodscientist@gmail.com
License: MIT
License-File: LICENSE
